tb_rest_client/__init__.py
tb_rest_client/api/__init__.py
tb_rest_client/api/api_ce/__init__.py
tb_rest_client/api/api_ce/admin_controller_api.py
tb_rest_client/api/api_ce/alarm_comment_controller_api.py
tb_rest_client/api/api_ce/alarm_controller_api.py
tb_rest_client/api/api_ce/asset_controller_api.py
tb_rest_client/api/api_ce/asset_profile_controller_api.py
tb_rest_client/api/api_ce/audit_log_controller_api.py
tb_rest_client/api/api_ce/auth_controller_api.py
tb_rest_client/api/api_ce/component_descriptor_controller_api.py
tb_rest_client/api/api_ce/customer_controller_api.py
tb_rest_client/api/api_ce/dashboard_controller_api.py
tb_rest_client/api/api_ce/device_api_controller_api.py
tb_rest_client/api/api_ce/device_connectivity_controller_api.py
tb_rest_client/api/api_ce/device_controller_api.py
tb_rest_client/api/api_ce/device_profile_controller_api.py
tb_rest_client/api/api_ce/domain_controller_api.py
tb_rest_client/api/api_ce/edge_controller_api.py
tb_rest_client/api/api_ce/edge_event_controller_api.py
tb_rest_client/api/api_ce/entities_version_control_controller_api.py
tb_rest_client/api/api_ce/entity_query_controller_api.py
tb_rest_client/api/api_ce/entity_relation_controller_api.py
tb_rest_client/api/api_ce/entity_view_controller_api.py
tb_rest_client/api/api_ce/event_controller_api.py
tb_rest_client/api/api_ce/image_controller_api.py
tb_rest_client/api/api_ce/login_endpoint_api.py
tb_rest_client/api/api_ce/lwm_2m_controller_api.py
tb_rest_client/api/api_ce/mail_config_template_controller_api.py
tb_rest_client/api/api_ce/mobile_app_bundle_controller_api.py
tb_rest_client/api/api_ce/mobile_app_controller_api.py
tb_rest_client/api/api_ce/mobile_application_controller_api.py
tb_rest_client/api/api_ce/notification_controller_api.py
tb_rest_client/api/api_ce/notification_rule_controller_api.py
tb_rest_client/api/api_ce/notification_target_controller_api.py
tb_rest_client/api/api_ce/notification_template_controller_api.py
tb_rest_client_fork-3.9.2.dist-info/LICENSE
tb_rest_client_fork-3.9.2.dist-info/METADATA
tb_rest_client_fork-3.9.2.dist-info/WHEEL
tb_rest_client_fork-3.9.2.dist-info/RECORD
